{"_type":"export","__export_format":4,"__export_date":"2022-09-23T14:36:05.640Z","__export_source":"insomnia.desktop.app:v2022.5.1","resources":[{"_id":"req_bd53b021fcc446a99c5fb52cd8cf3f89","parentId":"wrk_c038eb804a074a0dadba31c48e7bb53e","modified":1663940701000,"created":1663940448675,"url":"http://127.0.0.1:8000/api/courses/","name":"Traer todos los cursos","description":"","method":"GET","body":{"mimeType":"application/json","text":""},"parameters":[],"headers":[{"name":"Content-Type","value":"application/json","id":"pair_5bc4eead211d4ce687e878efe4bbe40f"}],"authentication":{},"metaSortKey":-1663940448675,"isPrivate":false,"settingStoreCookies":true,"settingSendCookies":true,"settingDisableRenderRequestBody":false,"settingEncodeUrl":true,"settingRebuildPath":true,"settingFollowRedirects":"global","_type":"request"},{"_id":"wrk_c038eb804a074a0dadba31c48e7bb53e","parentId":null,"modified":1661517271474,"created":1661517271474,"name":"New Document","description":"","scope":"design","_type":"workspace"},{"_id":"req_4416b06aa3e7499db320b290bc1ba095","parentId":"wrk_c038eb804a074a0dadba31c48e7bb53e","modified":1663941920073,"created":1663940433867,"url":"http://127.0.0.1:8000/api/courses/4","name":"Traer curso por id","description":"","method":"GET","body":{},"parameters":[],"headers":[],"authentication":{},"metaSortKey":-1663940433867,"isPrivate":false,"settingStoreCookies":true,"settingSendCookies":true,"settingDisableRenderRequestBody":false,"settingEncodeUrl":true,"settingRebuildPath":true,"settingFollowRedirects":"global","_type":"request"},{"_id":"req_c53e77227c52482488bcf0eea811b03f","parentId":"wrk_c038eb804a074a0dadba31c48e7bb53e","modified":1663941960475,"created":1663940404852,"url":"http://127.0.0.1:8000/api/courses/4","name":"Eliminar curso por id","description":"","method":"DELETE","body":{},"parameters":[],"headers":[],"authentication":{},"metaSortKey":-1663940404852,"isPrivate":false,"settingStoreCookies":true,"settingSendCookies":true,"settingDisableRenderRequestBody":false,"settingEncodeUrl":true,"settingRebuildPath":true,"settingFollowRedirects":"global","_type":"request"},{"_id":"req_61c6b46a45254db08d77360b8dd2e071","parentId":"wrk_c038eb804a074a0dadba31c48e7bb53e","modified":1663941953706,"created":1663940378043,"url":"http://127.0.0.1:8000/api/courses/1","name":"Actualizar curso por id","description":"","method":"PUT","body":{"mimeType":"application/json","text":"{\n\t\"title\": \"phyton\",\n\t\"description\": \"buen curso\"\n}"},"parameters":[],"headers":[{"id":"pair_ab86c3d0da0e4441a9949aa153f253a5","name":"Content-Type","value":"application/json","description":""}],"authentication":{},"metaSortKey":-1663940378043,"isPrivate":false,"settingStoreCookies":true,"settingSendCookies":true,"settingDisableRenderRequestBody":false,"settingEncodeUrl":true,"settingRebuildPath":true,"settingFollowRedirects":"global","_type":"request"},{"_id":"req_78785e2f437740b59b16bdef25acc3ea","parentId":"wrk_c038eb804a074a0dadba31c48e7bb53e","modified":1663941894082,"created":1663940334276,"url":"http://127.0.0.1:8000/api/courses","name":"Crear un nuevo curso","description":"","method":"POST","body":{"mimeType":"application/json","text":"{\n\t\t\t\t\"title\": \"curso numero 5\",\n        \"description\": \"este es el numero 5\",\n        \"weeks\": 28,\n        \"enroll_cost\": 2.5,\n        \"minimum_skill\": \"habilidad para jugar futbol\",\n        \"bootcamp_id\": 3\n}"},"parameters":[],"headers":[{"name":"Content-Type","value":"application/json","id":"pair_724f63c8558142f29a91cfe03045e194"}],"authentication":{},"metaSortKey":-1663940334276,"isPrivate":false,"settingStoreCookies":true,"settingSendCookies":true,"settingDisableRenderRequestBody":false,"settingEncodeUrl":true,"settingRebuildPath":true,"settingFollowRedirects":"global","_type":"request"},{"_id":"req_5c21d34ff8f64162a25570e9c697a8e1","parentId":"fld_2501244c1f1846cdb6f13c6a09af40ae","modified":1662137306518,"created":1661531673622,"url":"http://127.0.0.1:8000/api/bootcamps/4","name":"Eliminar bootcamp por id","description":"","method":"DELETE","body":{},"parameters":[],"headers":[],"authentication":{},"metaSortKey":-1661531673622,"isPrivate":false,"settingStoreCookies":true,"settingSendCookies":true,"settingDisableRenderRequestBody":false,"settingEncodeUrl":true,"settingRebuildPath":true,"settingFollowRedirects":"global","_type":"request"},{"_id":"fld_2501244c1f1846cdb6f13c6a09af40ae","parentId":"wrk_c038eb804a074a0dadba31c48e7bb53e","modified":1661531490560,"created":1661531490560,"name":"campamento-software-sena","description":"","environment":{},"environmentPropertyOrder":null,"metaSortKey":-1661531490560,"_type":"request_group"},{"_id":"req_1844b74d16df49a2b0eceb32384a366d","parentId":"fld_2501244c1f1846cdb6f13c6a09af40ae","modified":1663941746681,"created":1661531648702,"url":"http://127.0.0.1:8000/api/bootcamps/3","name":"Actualizar bootcamp por id","description":"","method":"PUT","body":{"mimeType":"application/json","text":"{\n\t\"name\": \"Kotlyn\",\n\t\"description\": \"Kotlyn for beginners\"\n}"},"parameters":[],"headers":[{"id":"pair_f246abd4312b4961a4f016eb42ad28e7","name":"Content-Type","value":"application/json","description":""}],"authentication":{},"metaSortKey":-1661531648702,"isPrivate":false,"settingStoreCookies":true,"settingSendCookies":true,"settingDisableRenderRequestBody":false,"settingEncodeUrl":true,"settingRebuildPath":true,"settingFollowRedirects":"global","_type":"request"},{"_id":"req_160df754a7a04221b2aaa04fa0eef2a0","parentId":"fld_2501244c1f1846cdb6f13c6a09af40ae","modified":1663941512683,"created":1661531607158,"url":"http://127.0.0.1:8000/api/bootcamps","name":"crear un nuevo bootcamp","description":"","method":"POST","body":{"mimeType":"application/json","text":"{\n\t\t\t\t\"name\": \"Net for beginners\",\n        \"website\": \"ASP.NET\",\n        \"phone\": \"(555)555-55-55\",\n        \"description\": \"ASP.NET MVC\",\n        \"average_rating\": 1,\n        \"average_cost\": 0,\n        \"user_id\": 1\n}"},"parameters":[],"headers":[{"id":"pair_f7b828fa932f4ad09d89174985618ab5","name":"Content-Type","value":"application/json","description":""}],"authentication":{},"metaSortKey":-1661531607158,"isPrivate":false,"settingStoreCookies":true,"settingSendCookies":true,"settingDisableRenderRequestBody":false,"settingEncodeUrl":true,"settingRebuildPath":true,"settingFollowRedirects":"global","_type":"request"},{"_id":"req_5f9b09c576b74bd4aa70ac15ceb3608f","parentId":"fld_2501244c1f1846cdb6f13c6a09af40ae","modified":1662133960427,"created":1661531578335,"url":"http://127.0.0.1:8000/api/bootcamps/3","name":"traer un bootcamp por id","description":"","method":"GET","body":{},"parameters":[],"headers":[],"authentication":{},"metaSortKey":-1661531578335,"isPrivate":false,"settingStoreCookies":true,"settingSendCookies":true,"settingDisableRenderRequestBody":false,"settingEncodeUrl":true,"settingRebuildPath":true,"settingFollowRedirects":"global","_type":"request"},{"_id":"req_d4a8304ce8e84c8ca5831a11d60a509e","parentId":"fld_2501244c1f1846cdb6f13c6a09af40ae","modified":1663938430818,"created":1661531517713,"url":"http://127.0.0.1:8000/api/bootcamps","name":"traer todos los bootcamps","description":"","method":"GET","body":{},"parameters":[],"headers":[],"authentication":{},"metaSortKey":-1661531517713,"isPrivate":false,"settingStoreCookies":true,"settingSendCookies":true,"settingDisableRenderRequestBody":false,"settingEncodeUrl":true,"settingRebuildPath":true,"settingFollowRedirects":"global","_type":"request"},{"_id":"req_450bb7609ed14f8a94d58403a9bbcbce","parentId":"wrk_c038eb804a074a0dadba31c48e7bb53e","modified":1661517271510,"created":1661517271510,"url":"","name":"New Request","description":"","method":"GET","body":{},"parameters":[],"headers":[],"authentication":{},"metaSortKey":-1661517271510,"isPrivate":false,"settingStoreCookies":true,"settingSendCookies":true,"settingDisableRenderRequestBody":false,"settingEncodeUrl":true,"settingRebuildPath":true,"settingFollowRedirects":"global","_type":"request"},{"_id":"env_638bdfb2f7f76166ef4fd9bdd350d17ba174de51","parentId":"wrk_c038eb804a074a0dadba31c48e7bb53e","modified":1661517271500,"created":1661517271500,"name":"Base Environment","data":{},"dataPropertyOrder":null,"color":null,"isPrivate":false,"metaSortKey":1661517271500,"_type":"environment"},{"_id":"jar_638bdfb2f7f76166ef4fd9bdd350d17ba174de51","parentId":"wrk_c038eb804a074a0dadba31c48e7bb53e","modified":1661517271505,"created":1661517271505,"name":"Default Jar","cookies":[],"_type":"cookie_jar"},{"_id":"spc_296a55a3986a44159acd6cbd80964ac5","parentId":"wrk_c038eb804a074a0dadba31c48e7bb53e","modified":1663938203708,"created":1661517271493,"fileName":"campamento-software-sena","contents":"{\"_type\":\"export\",\"__export_format\":4,\"__export_date\":\"2022-09-02T16:50:05.938Z\",\"__export_source\":\"insomnia.desktop.app:v2022.5.1\",\"resources\":[{\"_id\":\"req_5c21d34ff8f64162a25570e9c697a8e1\",\"parentId\":\"fld_2501244c1f1846cdb6f13c6a09af40ae\",\"modified\":1662137306518,\"created\":1661531673622,\"url\":\"http://127.0.0.1:8000/api/bootcamps/4\",\"name\":\"Eliminar bootcamp por id\",\"description\":\"\",\"method\":\"DELETE\",\"body\":{},\"parameters\":[],\"headers\":[],\"authentication\":{},\"metaSortKey\":-1661531673622,\"isPrivate\":false,\"settingStoreCookies\":true,\"settingSendCookies\":true,\"settingDisableRenderRequestBody\":false,\"settingEncodeUrl\":true,\"settingRebuildPath\":true,\"settingFollowRedirects\":\"global\",\"_type\":\"request\"},{\"_id\":\"fld_2501244c1f1846cdb6f13c6a09af40ae\",\"parentId\":\"wrk_c038eb804a074a0dadba31c48e7bb53e\",\"modified\":1661531490560,\"created\":1661531490560,\"name\":\"campamento-software-sena\",\"description\":\"\",\"environment\":{},\"environmentPropertyOrder\":null,\"metaSortKey\":-1661531490560,\"_type\":\"request_group\"},{\"_id\":\"wrk_c038eb804a074a0dadba31c48e7bb53e\",\"parentId\":null,\"modified\":1661517271474,\"created\":1661517271474,\"name\":\"New Document\",\"description\":\"\",\"scope\":\"design\",\"_type\":\"workspace\"},{\"_id\":\"req_1844b74d16df49a2b0eceb32384a366d\",\"parentId\":\"fld_2501244c1f1846cdb6f13c6a09af40ae\",\"modified\":1662137111933,\"created\":1661531648702,\"url\":\"http://127.0.0.1:8000/api/bootcamps/3\",\"name\":\"Actualizar bootcamp por id\",\"description\":\"\",\"method\":\"PUT\",\"body\":{\"mimeType\":\"application/json\",\"text\":\"{\\n\\t\\\"name\\\": \\\"Kotlyn\\\",\\n\\t\\\"description\\\": \\\"Kotlyn for beginners\\\"\\n}\"},\"parameters\":[],\"headers\":[{\"id\":\"pair_f246abd4312b4961a4f016eb42ad28e7\",\"name\":\"Content-Type\",\"value\":\"application/json\",\"description\":\"\"}],\"authentication\":{},\"metaSortKey\":-1661531648702,\"isPrivate\":false,\"settingStoreCookies\":true,\"settingSendCookies\":true,\"settingDisableRenderRequestBody\":false,\"settingEncodeUrl\":true,\"settingRebuildPath\":true,\"settingFollowRedirects\":\"global\",\"_type\":\"request\"},{\"_id\":\"req_160df754a7a04221b2aaa04fa0eef2a0\",\"parentId\":\"fld_2501244c1f1846cdb6f13c6a09af40ae\",\"modified\":1662135658758,\"created\":1661531607158,\"url\":\"http://127.0.0.1:8000/api/bootcamps\",\"name\":\"crear un nuevo bootcamp\",\"description\":\"\",\"method\":\"POST\",\"body\":{\"mimeType\":\"application/json\",\"text\":\"{\\n\\t\\t\\t\\t\\\"name\\\": \\\"Net for beginners\\\",\\n        \\\"website\\\": \\\"ASP.NET\\\",\\n        \\\"phone\\\": \\\"(555)555-55-55\\\",\\n        \\\"description\\\": \\\"ASP.NET MVC\\\",\\n        \\\"average_rating\\\": 1,\\n        \\\"average_cost\\\": 0,\\n        \\\"user_id\\\": 1\\n}\"},\"parameters\":[],\"headers\":[{\"id\":\"pair_f7b828fa932f4ad09d89174985618ab5\",\"name\":\"Content-Type\",\"value\":\"application/json\",\"description\":\"\"}],\"authentication\":{},\"metaSortKey\":-1661531607158,\"isPrivate\":false,\"settingStoreCookies\":true,\"settingSendCookies\":true,\"settingDisableRenderRequestBody\":false,\"settingEncodeUrl\":true,\"settingRebuildPath\":true,\"settingFollowRedirects\":\"global\",\"_type\":\"request\"},{\"_id\":\"req_5f9b09c576b74bd4aa70ac15ceb3608f\",\"parentId\":\"fld_2501244c1f1846cdb6f13c6a09af40ae\",\"modified\":1662133960427,\"created\":1661531578335,\"url\":\"http://127.0.0.1:8000/api/bootcamps/3\",\"name\":\"traer un bootcamp por id\",\"description\":\"\",\"method\":\"GET\",\"body\":{},\"parameters\":[],\"headers\":[],\"authentication\":{},\"metaSortKey\":-1661531578335,\"isPrivate\":false,\"settingStoreCookies\":true,\"settingSendCookies\":true,\"settingDisableRenderRequestBody\":false,\"settingEncodeUrl\":true,\"settingRebuildPath\":true,\"settingFollowRedirects\":\"global\",\"_type\":\"request\"},{\"_id\":\"req_d4a8304ce8e84c8ca5831a11d60a509e\",\"parentId\":\"fld_2501244c1f1846cdb6f13c6a09af40ae\",\"modified\":1661531850736,\"created\":1661531517713,\"url\":\"http://127.0.0.1:8000/api/bootcamps\",\"name\":\"traer todos los bootcamps\",\"description\":\"\",\"method\":\"GET\",\"body\":{},\"parameters\":[],\"headers\":[],\"authentication\":{},\"metaSortKey\":-1661531517713,\"isPrivate\":false,\"settingStoreCookies\":true,\"settingSendCookies\":true,\"settingDisableRenderRequestBody\":false,\"settingEncodeUrl\":true,\"settingRebuildPath\":true,\"settingFollowRedirects\":\"global\",\"_type\":\"request\"},{\"_id\":\"req_450bb7609ed14f8a94d58403a9bbcbce\",\"parentId\":\"wrk_c038eb804a074a0dadba31c48e7bb53e\",\"modified\":1661517271510,\"created\":1661517271510,\"url\":\"\",\"name\":\"New Request\",\"description\":\"\",\"method\":\"GET\",\"body\":{},\"parameters\":[],\"headers\":[],\"authentication\":{},\"metaSortKey\":-1661517271510,\"isPrivate\":false,\"settingStoreCookies\":true,\"settingSendCookies\":true,\"settingDisableRenderRequestBody\":false,\"settingEncodeUrl\":true,\"settingRebuildPath\":true,\"settingFollowRedirects\":\"global\",\"_type\":\"request\"},{\"_id\":\"env_638bdfb2f7f76166ef4fd9bdd350d17ba174de51\",\"parentId\":\"wrk_c038eb804a074a0dadba31c48e7bb53e\",\"modified\":1661517271500,\"created\":1661517271500,\"name\":\"Base Environment\",\"data\":{},\"dataPropertyOrder\":null,\"color\":null,\"isPrivate\":false,\"metaSortKey\":1661517271500,\"_type\":\"environment\"},{\"_id\":\"jar_638bdfb2f7f76166ef4fd9bdd350d17ba174de51\",\"parentId\":\"wrk_c038eb804a074a0dadba31c48e7bb53e\",\"modified\":1661517271505,\"created\":1661517271505,\"name\":\"Default Jar\",\"cookies\":[],\"_type\":\"cookie_jar\"},{\"_id\":\"spc_296a55a3986a44159acd6cbd80964ac5\",\"parentId\":\"wrk_c038eb804a074a0dadba31c48e7bb53e\",\"modified\":1661532610521,\"created\":1661517271493,\"fileName\":\"campamento-software-sena\",\"contents\":\"\",\"contentType\":\"yaml\",\"_type\":\"api_spec\"},{\"_id\":\"uts_0c263cba4f4d408c80bafa4895a658af\",\"parentId\":\"wrk_c038eb804a074a0dadba31c48e7bb53e\",\"modified\":1661517271512,\"created\":1661517271512,\"name\":\"Example Test Suite\",\"_type\":\"unit_test_suite\"}]}","contentType":"yaml","_type":"api_spec"},{"_id":"uts_0c263cba4f4d408c80bafa4895a658af","parentId":"wrk_c038eb804a074a0dadba31c48e7bb53e","modified":1661517271512,"created":1661517271512,"name":"Example Test Suite","_type":"unit_test_suite"}]}